tablemango/__init__.py
tablemango/tablemango.py
tablemango/tablemango12.py
tablemango12-0.2.dist-info/LICENSE
tablemango12-0.2.dist-info/METADATA
tablemango12-0.2.dist-info/WHEEL
tablemango12-0.2.dist-info/top_level.txt
tablemango12-0.2.dist-info/RECORD
