Metadata-Version: 2.1
Name: tablemango12
Version: 0.2
Summary: Solve N-Queens or Tower of Hanoi and copy results to clipboard
Author: Your Name
License-File: LICENSE
Requires-Dist: pyperclip
